helpscout/__init__.py
helpscout/auth_proxy.py
helpscout/base_api.py
helpscout/base_model.py
helpscout/exceptions.py
helpscout/apis/__init__.py
helpscout/apis/conversations.py
helpscout/apis/customers.py
helpscout/apis/mailboxes.py
helpscout/apis/tags.py
helpscout/apis/teams.py
helpscout/apis/users.py
helpscout/apis/web_hook.py
helpscout/domain/__init__.py
helpscout/models/__init__.py
helpscout/models/address.py
helpscout/models/attachment.py
helpscout/models/attachment_data.py
helpscout/models/base_conversation.py
helpscout/models/chat.py
helpscout/models/conversation.py
helpscout/models/custom_field.py
helpscout/models/customer.py
helpscout/models/email.py
helpscout/models/field.py
helpscout/models/folder.py
helpscout/models/mailbox.py
helpscout/models/mailbox_ref.py
helpscout/models/option.py
helpscout/models/person.py
helpscout/models/phone.py
helpscout/models/rating.py
helpscout/models/search_conversation.py
helpscout/models/search_customer.py
helpscout/models/social_profile.py
helpscout/models/source.py
helpscout/models/tag.py
helpscout/models/thread.py
helpscout/models/user.py
helpscout/models/web_hook.py
helpscout/models/web_hook_event.py
helpscout/models/website.py
helpscout/models/workflow.py
helpscout/request_paginator/__init__.py
helpscout/tests/__init__.py
helpscout/tests/api_common.py
helpscout/tests/test_api_conversations.py
helpscout/tests/test_api_web_hook.py
helpscout/tests/test_auth_proxy.py
helpscout/tests/test_base_api.py
helpscout/tests/test_base_model.py
helpscout/tests/test_domain.py
helpscout/tests/test_exceptions.py
helpscout/tests/test_helpscout.py
helpscout/tests/test_helpscout_web_hook.py
helpscout/tests/test_helpscout_web_hook_event.py
helpscout/tests/test_request_paginator.py
helpscout/web_hook/__init__.py
helpscout-0.0.7b235.dist-info/DESCRIPTION.rst
helpscout-0.0.7b235.dist-info/METADATA
helpscout-0.0.7b235.dist-info/RECORD
helpscout-0.0.7b235.dist-info/WHEEL
helpscout-0.0.7b235.dist-info/metadata.json
helpscout-0.0.7b235.dist-info/top_level.txt
