Metadata-Version: 2.0
Name: helpscout
Version: 0.0.7b235
Summary: This library allows you to interact with HelpScout using Python.
Home-page: https://laslabs.github.io/python-helpscout
Author: LasLabs Inc.
Author-email: support@laslabs.com
License: MIT
Download-URL: https://github.com/LasLabs/python-helpscout
Platform: UNKNOWN
Classifier: Development Status :: 4 - Beta
Classifier: Environment :: Console
Classifier: Intended Audience :: Developers
Classifier: License :: OSI Approved :: MIT License
Classifier: Programming Language :: Python
Classifier: Programming Language :: Python :: 2
Classifier: Programming Language :: Python :: 2.7
Classifier: Programming Language :: Python :: 3
Classifier: Programming Language :: Python :: 3.4
Classifier: Programming Language :: Python :: 3.5
Classifier: Programming Language :: Python :: 3.6
Classifier: Topic :: Software Development :: Libraries :: Python Modules
Requires-Dist: properties (>=0.3.6b0)
Requires-Dist: requests (>=2.18.4)
Requires-Dist: six (>=1.1.0)
